{
  "lastUpdated": "2026-06-30T09:05:35.285Z",
  "rates": [
    {
      "bank": "BFA",
      "currency": "USD",
      "sell": "981,013"
    },
    {
      "bank": "BFA",
      "currency": "EUR",
      "sell": "1145,925"
    },
    {
      "bank": "BFA",
      "currency": "NAD",
      "sell": "61,058"
    },
    {
      "bank": "BFA",
      "currency": "GBP",
      "sell": "1329,388"
    },
    {
      "bank": "BAI",
      "currency": "EUR",
      "sell": "1153,764"
    },
    {
      "bank": "BAI",
      "currency": "GBP",
      "sell": "1307,0307"
    },
    {
      "bank": "BAI",
      "currency": "USD",
      "sell": "987,7234"
    },
    {
      "bank": "BAI",
      "currency": "ZAR",
      "sell": "61,4463"
    },
    {
      "bank": "BNA",
      "currency": "USD",
      "sell": "912,57"
    },
    {
      "bank": "BNA",
      "currency": "EUR",
      "sell": "1065,977"
    },
    {
      "bank": "BNA",
      "currency": "ZAR",
      "sell": "56,771"
    }
  ]
}