{
  "usableSessionsCount": 2,
  "retiredSessionsCount": 0,
  "sessions": [
    {
      "id": "session_mpW3dQRT6H",
      "cookieJar": {
        "version": "tough-cookie@6.0.0",
        "storeType": "MemoryCookieStore",
        "rejectPublicSuffixes": true,
        "enableLooseMode": false,
        "allowSpecialUseDomain": true,
        "prefixSecurity": "silent",
        "cookies": []
      },
      "userData": {},
      "maxErrorScore": 3,
      "errorScoreDecrement": 0.5,
      "expiresAt": "2026-07-14T14:50:27.827Z",
      "createdAt": "2026-07-14T14:00:27.827Z",
      "usageCount": 0,
      "maxUsageCount": 50,
      "errorScore": 0
    },
    {
      "id": "session_PfXGnl4pZl",
      "cookieJar": {
        "version": "tough-cookie@6.0.0",
        "storeType": "MemoryCookieStore",
        "rejectPublicSuffixes": true,
        "enableLooseMode": false,
        "allowSpecialUseDomain": true,
        "prefixSecurity": "silent",
        "cookies": []
      },
      "userData": {},
      "maxErrorScore": 3,
      "errorScoreDecrement": 0.5,
      "expiresAt": "2026-07-14T14:50:27.832Z",
      "createdAt": "2026-07-14T14:00:27.832Z",
      "usageCount": 0,
      "maxUsageCount": 50,
      "errorScore": 0
    }
  ]
}